{
	"com.badlogic.gdx.graphics.Color":
	{
		"white":	{ "a": 1, "b": 1, "g": 1, "r": 1 },
		"grey": 	{ "r": 0.3137255, "g": 0.3137255, "b": 0.3137255, "a": 1 },
		"black":	{ "a": 1, "b": 0, "g": 0, "r": 0 }
	},
	
    "com.badlogic.gdx.graphics.g2d.BitmapFont":
    {
        "default-font":	{ "file": "fonts/calibri-18pt.fnt" },
        "small-font": {"file": "fonts/calibri-18pt.fnt"},
        "large-font": {"file": "fonts/calibri-24pt.fnt"},
        
        "pixel-font-large": {"file": "fonts/pixmix-20pt.fnt"},
        "pixel-font": {"file": "fonts/pixmix-16pt.fnt"},
        "pixel-font-small": {"file": "fonts/pixmix-12pt.fnt"}
    },
    
	"com.badlogic.gdx.scenes.scene2d.ui.Label$LabelStyle":
	{
        "default": { "font": "default-font" }
    },
    
	"com.badlogic.gdx.scenes.scene2d.ui.Window$WindowStyle":
	{
		"default": { "titleFont": "pixel-font-large", "titleFontColor": "grey", "background": "main_menu_background", "stageBackground": "main_menu_background"}
	},

	"com.badlogic.gdx.scenes.scene2d.ui.TextButton$TextButtonStyle":
	{
		"default": { "font": "pixel-font-small", "fontColor": "black", "up": "button_background" }
	}
}